litncov/__init__.py
litncov/__main__.py
litncov/main.py
litncov/user.py
litncov/util.py
litncov-2.2.1.dist-info/LICENSE
litncov-2.2.1.dist-info/METADATA
litncov-2.2.1.dist-info/WHEEL
litncov-2.2.1.dist-info/entry_points.txt
litncov-2.2.1.dist-info/top_level.txt
litncov-2.2.1.dist-info/RECORD
