Metadata-Version: 2.1
Name: litncov
Version: 2.2.1
Summary: A ncov report library and tool for LIT(Luoyang Institute of Science and Technology)
Home-page: http://github.com/icepie/lit-ncov-report
Author: Tea
Author-email: icepie.dev@gmail.com
License: MIT
Keywords: lit,ncov,report,11070
Platform: UNKNOWN
Requires-Python: >=3.6
Requires-Dist: rich
Requires-Dist: requests
Requires-Dist: pytz
